chpeck2.py
chpeck2-0.0.1.dist-info/LICENSE.txt
chpeck2-0.0.1.dist-info/METADATA
chpeck2-0.0.1.dist-info/WHEEL
chpeck2-0.0.1.dist-info/top_level.txt
chpeck2-0.0.1.dist-info/RECORD
