Metadata-Version: 2.2
Name: chpeck2
Version: 0.0.1
Summary: Unknown description. Just a piece of garbage.
Author: Anonymous
License: Copyright (C) 08.03.25 ...
Classifier: Programming Language :: Python :: 3
Classifier: Operating System :: OS Independent
Requires-Python: >=3.10
License-File: LICENSE.txt
Requires-Dist: requests>=2.32.3
Requires-Dist: bs4>=4.13.3
Requires-Dist: pandas>=2.2.3
